meltingface/__init__.py
meltingface/hub.py
meltingface/prompt.py
meltingface/utils.py
meltingface-0.1.3.dist-info/METADATA
meltingface-0.1.3.dist-info/WHEEL
meltingface-0.1.3.dist-info/entry_points.txt
meltingface-0.1.3.dist-info/RECORD
