Metadata-Version: 2.4
Name: meltingface
Version: 0.1.3
Summary: Python SDK for meltingface.eu
Author: Kasper Junge
Requires-Python: >=3.12
Requires-Dist: requests>=2.32.3
